aiopinecone/__init__.py
aiopinecone/client.py
aiopinecone/retry.py
aiopinecone/schemas/__init__.py
aiopinecone/schemas/custom.py
aiopinecone/schemas/generated.py
aiopinecone-0.1.7.dist-info/LICENSE
aiopinecone-0.1.7.dist-info/WHEEL
aiopinecone-0.1.7.dist-info/METADATA
aiopinecone-0.1.7.dist-info/RECORD
